easy-install.pth
setuptools.pth
site.py
uclmr_jack-0.2.1-py3.6.egg
__pycache__/site.cpython-36.pyc
uclmr_jack-0.2.1.data/scripts/chardetect
uclmr_jack-0.2.1.data/scripts/codecov
uclmr_jack-0.2.1.data/scripts/coverage
uclmr_jack-0.2.1.data/scripts/coverage-3.6
uclmr_jack-0.2.1.data/scripts/coverage3
uclmr_jack-0.2.1.data/scripts/easy_install
uclmr_jack-0.2.1.data/scripts/easy_install-3.6
uclmr_jack-0.2.1.data/scripts/ftfy
uclmr_jack-0.2.1.data/scripts/jsonschema
uclmr_jack-0.2.1.data/scripts/pep8
uclmr_jack-0.2.1.data/scripts/pip
uclmr_jack-0.2.1.data/scripts/pip3
uclmr_jack-0.2.1.data/scripts/pip3.6
uclmr_jack-0.2.1.data/scripts/py.test
uclmr_jack-0.2.1.data/scripts/pytest
uclmr_jack-0.2.1.data/scripts/tqdm
uclmr_jack-0.2.1.dist-info/METADATA
uclmr_jack-0.2.1.dist-info/RECORD
uclmr_jack-0.2.1.dist-info/WHEEL
uclmr_jack-0.2.1.dist-info/top_level.txt
